README.md
setup.py
PyGz1.egg-info/PKG-INFO
PyGz1.egg-info/SOURCES.txt
PyGz1.egg-info/dependency_links.txt
PyGz1.egg-info/requires.txt
PyGz1.egg-info/top_level.txt
pygz1/__init__.py
pygz1/network.py
pygz1/utils.py