Metadata-Version: 2.1
Name: PyGz1
Version: 0.4.0
Summary: A Python library for Internet interaction.
Author: MrGengar
Author-email: rydikminecraft@gmail.com
Keywords: internet interaction requests
Classifier: Programming Language :: Python :: 3
Classifier: License :: OSI Approved :: MIT License
Classifier: Operating System :: OS Independent
